aio_geojson_query/__init__.py
aio_geojson_query/__version__.py
aio_geojson_query/consts.py
aio_geojson_query/feed.py
aio_geojson_query/feed_entry.py
aio_geojson_query/feed_manager.py
aio_geojson_query-0.0.4.dist-info/LICENSE
aio_geojson_query-0.0.4.dist-info/METADATA
aio_geojson_query-0.0.4.dist-info/WHEEL
aio_geojson_query-0.0.4.dist-info/top_level.txt
aio_geojson_query-0.0.4.dist-info/RECORD
