Metadata-Version: 2.1
Name: aio-geojson-query
Version: 0.0.4
Summary: A generalized client for aio-geojson-client
Home-page: https://github.com/exxamalte/python-aio-geojson-client
Author: Chris F Ravenscroft
Author-email: chris@voilaweb.com
License: MIT
Platform: UNKNOWN
Classifier: License :: OSI Approved :: MIT License
Classifier: Development Status :: 4 - Beta
Classifier: Programming Language :: Python
Classifier: Programming Language :: Python :: 3
Classifier: Programming Language :: Python :: 3.5
Classifier: Programming Language :: Python :: 3.6
Classifier: Programming Language :: Python :: 3.7
Classifier: Programming Language :: Python :: Implementation :: CPython
Classifier: Programming Language :: Python :: Implementation :: PyPy
Requires-Dist: aiodns
Requires-Dist: aiohttp (>=3.5.4)
Requires-Dist: aio-geojson-client (>=0.13)
Requires-Dist: python-dateutil (>=2.8.1)
Requires-Dist: pytz (>=2019.01)
